myver/__init__.py
myver/__main__.py
myver/cli.py
myver/config.py
myver/error.py
myver/files.py
myver/part.py
myver/version.py
myver-1.1.0.dist-info/LICENSE.md
myver-1.1.0.dist-info/METADATA
myver-1.1.0.dist-info/WHEEL
myver-1.1.0.dist-info/entry_points.txt
myver-1.1.0.dist-info/top_level.txt
myver-1.1.0.dist-info/RECORD
