Metadata-Version: 2.1
Name: myver
Version: 1.1.0
Summary: Development tool for configuring and altering software versions.
Home-page: https://github.com/mark-bromell/myver
Author: Mark Bromell
Author-email: markbromell.business@gmail.com
License: UNKNOWN
Project-URL: Issue Tracker, https://github.com/mark-bromell/myver/issues
Project-URL: Source Code, https://github.com/mark-bromell/myver
Platform: UNKNOWN
Classifier: Programming Language :: Python :: 3
Classifier: License :: OSI Approved :: MIT License
Classifier: Operating System :: OS Independent
Requires-Python: >=3.7
License-File: LICENSE.md
Requires-Dist: ruamel.yaml (==0.17.17)
Requires-Dist: jinja2 (==3.0.3)
